pyramid_swagger/__about__.py
pyramid_swagger/__init__.py
pyramid_swagger/api.py
pyramid_swagger/exceptions.py
pyramid_swagger/ingest.py
pyramid_swagger/load_schema.py
pyramid_swagger/model.py
pyramid_swagger/renderer.py
pyramid_swagger/spec.py
pyramid_swagger/tween.py
pyramid_swagger-2.7.0.dist-info/LICENSE
pyramid_swagger-2.7.0.dist-info/METADATA
pyramid_swagger-2.7.0.dist-info/WHEEL
pyramid_swagger-2.7.0.dist-info/top_level.txt
pyramid_swagger-2.7.0.dist-info/RECORD
