Metadata-Version: 2.1
Name: pyramid-swagger
Version: 2.7.0
Summary: Swagger tools for use in pyramid webapps
Home-page: https://github.com/striglia/pyramid_swagger
Author: Scott Triglia
Author-email: scott.triglia@gmail.com
License: BSD 3-clause
Keywords: pyramid swagger validation
Platform: UNKNOWN
Classifier: Development Status :: 5 - Production/Stable
Classifier: Intended Audience :: Developers
Classifier: Topic :: Software Development :: Libraries :: Python Modules
Classifier: Programming Language :: Python :: 2.7
Classifier: Programming Language :: Python :: 3.3
Classifier: Programming Language :: Python :: 3.4
Classifier: Programming Language :: Python :: 3.5
Requires-Dist: bravado-core (>=4.8.4)
Requires-Dist: jsonschema
Requires-Dist: pyramid
Requires-Dist: simplejson
